<?xml version="1.0" standalone="yes"?>
<NewDataSet>
  <xs:schema id="NewDataSet" xmlns="" xmlns:xs="http://www.w3.org/2001/XMLSchema" xmlns:msdata="urn:schemas-microsoft-com:xml-msdata">
    <xs:element name="NewDataSet" msdata:IsDataSet="true" msdata:UseCurrentLocale="true">
      <xs:complexType>
        <xs:choice minOccurs="0" maxOccurs="unbounded">
          <xs:element name="Prezzi">
            <xs:complexType>
              <xs:sequence>
                <xs:element name="Data" type="xs:string" minOccurs="0" />
                <xs:element name="Mercato" type="xs:string" minOccurs="0" />
                <xs:element name="Ora" type="xs:string" minOccurs="0" />
                <xs:element name="PUN" type="xs:string" minOccurs="0" />
                <xs:element name="NAT" type="xs:string" minOccurs="0" />
                <xs:element name="CALA" type="xs:string" minOccurs="0" />
                <xs:element name="CNOR" type="xs:string" minOccurs="0" />
                <xs:element name="CSUD" type="xs:string" minOccurs="0" />
                <xs:element name="NORD" type="xs:string" minOccurs="0" />
                <xs:element name="SARD" type="xs:string" minOccurs="0" />
                <xs:element name="SICI" type="xs:string" minOccurs="0" />
                <xs:element name="SUD" type="xs:string" minOccurs="0" />
                <xs:element name="AUST" type="xs:string" minOccurs="0" />
                <xs:element name="COAC" type="xs:string" minOccurs="0" />
                <xs:element name="COUP" type="xs:string" minOccurs="0" />
                <xs:element name="CORS" type="xs:string" minOccurs="0" />
                <xs:element name="FRAN" type="xs:string" minOccurs="0" />
                <xs:element name="GREC" type="xs:string" minOccurs="0" />
                <xs:element name="SLOV" type="xs:string" minOccurs="0" />
                <xs:element name="SVIZ" type="xs:string" minOccurs="0" />
                <xs:element name="BSP" type="xs:string" minOccurs="0" />
                <xs:element name="MALT" type="xs:string" minOccurs="0" />
                <xs:element name="XAUS" type="xs:string" minOccurs="0" />
                <xs:element name="XFRA" type="xs:string" minOccurs="0" />
                <xs:element name="MONT" type="xs:string" minOccurs="0" />
                <xs:element name="XGRE" type="xs:string" minOccurs="0" />
              </xs:sequence>
            </xs:complexType>
          </xs:element>
        </xs:choice>
      </xs:complexType>
    </xs:element>
  </xs:schema>
  <Prezzi>
    <Data>20240723</Data>
    <Mercato>MGP</Mercato>
    <Ora>1</Ora>
    <PUN>105,431590</PUN>
    <NAT>108,000000</NAT>
    <CALA>108,000000</CALA>
    <CNOR>108,000000</CNOR>
    <CSUD>108,000000</CSUD>
    <NORD>103,210000</NORD>
    <SARD>108,000000</SARD>
    <SICI>108,000000</SICI>
    <SUD>108,000000</SUD>
    <AUST>103,210000</AUST>
    <COAC>108,000000</COAC>
    <COUP>103,210000</COUP>
    <CORS>108,000000</CORS>
    <FRAN>103,210000</FRAN>
    <GREC>108,000000</GREC>
    <SLOV>103,210000</SLOV>
    <SVIZ>103,210000</SVIZ>
    <BSP>103,210000</BSP>
    <MALT>108,000000</MALT>
    <XAUS>103,210000</XAUS>
    <XFRA>103,210000</XFRA>
    <MONT>108,000000</MONT>
    <XGRE>108,000000</XGRE>
  </Prezzi>
  <Prezzi>
    <Data>20240723</Data>
    <Mercato>MGP</Mercato>
    <Ora>2</Ora>
    <PUN>103,579130</PUN>
    <NAT>105,000000</NAT>
    <CALA>105,100000</CALA>
    <CNOR>105,100000</CNOR>
    <CSUD>105,100000</CSUD>
    <NORD>102,300000</NORD>
    <SARD>105,100000</SARD>
    <SICI>105,100000</SICI>
    <SUD>105,100000</SUD>
    <AUST>102,300000</AUST>
    <COAC>105,100000</COAC>
    <COUP>102,300000</COUP>
    <CORS>105,100000</CORS>
    <FRAN>102,300000</FRAN>
    <GREC>105,100000</GREC>
    <SLOV>102,300000</SLOV>
    <SVIZ>102,300000</SVIZ>
    <BSP>102,300000</BSP>
    <MALT>105,100000</MALT>
    <XAUS>102,300000</XAUS>
    <XFRA>102,300000</XFRA>
    <MONT>105,100000</MONT>
    <XGRE>105,100000</XGRE>
  </Prezzi>
  <Prezzi>
    <Data>20240723</Data>
    <Mercato>MGP</Mercato>
    <Ora>3</Ora>
    <PUN>100,913450</PUN>
    <NAT>102,000000</NAT>
    <CALA>102,000000</CALA>
    <CNOR>102,000000</CNOR>
    <CSUD>102,000000</CSUD>
    <NORD>100,000000</NORD>
    <SARD>102,000000</SARD>
    <SICI>102,000000</SICI>
    <SUD>102,000000</SUD>
    <AUST>100,000000</AUST>
    <COAC>102,000000</COAC>
    <COUP>100,000000</COUP>
    <CORS>102,000000</CORS>
    <FRAN>100,000000</FRAN>
    <GREC>102,000000</GREC>
    <SLOV>100,000000</SLOV>
    <SVIZ>100,000000</SVIZ>
    <BSP>100,000000</BSP>
    <MALT>102,000000</MALT>
    <XAUS>100,000000</XAUS>
    <XFRA>100,000000</XFRA>
    <MONT>102,000000</MONT>
    <XGRE>102,000000</XGRE>
  </Prezzi>
  <Prezzi>
    <Data>20240723</Data>
    <Mercato>MGP</Mercato>
    <Ora>4</Ora>
    <PUN>100,000000</PUN>
    <NAT>100,000000</NAT>
    <CALA>100,000000</CALA>
    <CNOR>100,000000</CNOR>
    <CSUD>100,000000</CSUD>
    <NORD>100,000000</NORD>
    <SARD>100,000000</SARD>
    <SICI>100,000000</SICI>
    <SUD>100,000000</SUD>
    <AUST>100,000000</AUST>
    <COAC>100,000000</COAC>
    <COUP>100,000000</COUP>
    <CORS>100,000000</CORS>
    <FRAN>100,000000</FRAN>
    <GREC>100,000000</GREC>
    <SLOV>100,000000</SLOV>
    <SVIZ>100,000000</SVIZ>
    <BSP>100,000000</BSP>
    <MALT>100,000000</MALT>
    <XAUS>100,000000</XAUS>
    <XFRA>100,000000</XFRA>
    <MONT>100,000000</MONT>
    <XGRE>100,000000</XGRE>
  </Prezzi>
  <Prezzi>
    <Data>20240723</Data>
    <Mercato>MGP</Mercato>
    <Ora>5</Ora>
    <PUN>96,360000</PUN>
    <NAT>96,360000</NAT>
    <CALA>96,360000</CALA>
    <CNOR>96,360000</CNOR>
    <CSUD>96,360000</CSUD>
    <NORD>96,360000</NORD>
    <SARD>96,360000</SARD>
    <SICI>96,360000</SICI>
    <SUD>96,360000</SUD>
    <AUST>96,360000</AUST>
    <COAC>96,360000</COAC>
    <COUP>96,360000</COUP>
    <CORS>96,360000</CORS>
    <FRAN>96,360000</FRAN>
    <GREC>96,360000</GREC>
    <SLOV>96,360000</SLOV>
    <SVIZ>96,360000</SVIZ>
    <BSP>96,360000</BSP>
    <MALT>96,360000</MALT>
    <XAUS>96,360000</XAUS>
    <XFRA>96,360000</XFRA>
    <MONT>96,360000</MONT>
    <XGRE>96,360000</XGRE>
  </Prezzi>
  <Prezzi>
    <Data>20240723</Data>
    <Mercato>MGP</Mercato>
    <Ora>6</Ora>
    <PUN>99,047710</PUN>
    <NAT>99,000000</NAT>
    <CALA>99,047710</CALA>
    <CNOR>99,047710</CNOR>
    <CSUD>99,047710</CSUD>
    <NORD>99,047710</NORD>
    <SARD>99,047710</SARD>
    <SICI>99,047710</SICI>
    <SUD>99,047710</SUD>
    <AUST>99,047710</AUST>
    <COAC>99,047710</COAC>
    <COUP>99,047710</COUP>
    <CORS>99,047710</CORS>
    <FRAN>99,047710</FRAN>
    <GREC>99,047710</GREC>
    <SLOV>99,047710</SLOV>
    <SVIZ>99,047710</SVIZ>
    <BSP>99,047710</BSP>
    <MALT>99,047710</MALT>
    <XAUS>99,047710</XAUS>
    <XFRA>99,047710</XFRA>
    <MONT>99,047710</MONT>
    <XGRE>99,047710</XGRE>
  </Prezzi>
  <Prezzi>
    <Data>20240723</Data>
    <Mercato>MGP</Mercato>
    <Ora>7</Ora>
    <PUN>105,000000</PUN>
    <NAT>105,000000</NAT>
    <CALA>105,000000</CALA>
    <CNOR>105,000000</CNOR>
    <CSUD>105,000000</CSUD>
    <NORD>105,000000</NORD>
    <SARD>105,000000</SARD>
    <SICI>105,000000</SICI>
    <SUD>105,000000</SUD>
    <AUST>105,000000</AUST>
    <COAC>105,000000</COAC>
    <COUP>105,000000</COUP>
    <CORS>105,000000</CORS>
    <FRAN>105,000000</FRAN>
    <GREC>105,000000</GREC>
    <SLOV>105,000000</SLOV>
    <SVIZ>105,000000</SVIZ>
    <BSP>105,000000</BSP>
    <MALT>105,000000</MALT>
    <XAUS>105,000000</XAUS>
    <XFRA>105,000000</XFRA>
    <MONT>105,000000</MONT>
    <XGRE>105,000000</XGRE>
  </Prezzi>
  <Prezzi>
    <Data>20240723</Data>
    <Mercato>MGP</Mercato>
    <Ora>8</Ora>
    <PUN>115,210470</PUN>
    <NAT>115,430000</NAT>
    <CALA>112,610000</CALA>
    <CNOR>115,430000</CNOR>
    <CSUD>115,430000</CSUD>
    <NORD>115,430000</NORD>
    <SARD>115,430000</SARD>
    <SICI>112,610000</SICI>
    <SUD>115,430000</SUD>
    <AUST>115,430000</AUST>
    <COAC>115,430000</COAC>
    <COUP>115,430000</COUP>
    <CORS>115,430000</CORS>
    <FRAN>115,430000</FRAN>
    <GREC>115,430000</GREC>
    <SLOV>115,430000</SLOV>
    <SVIZ>115,430000</SVIZ>
    <BSP>115,430000</BSP>
    <MALT>112,610000</MALT>
    <XAUS>115,430000</XAUS>
    <XFRA>115,430000</XFRA>
    <MONT>115,430000</MONT>
    <XGRE>115,430000</XGRE>
  </Prezzi>
  <Prezzi>
    <Data>20240723</Data>
    <Mercato>MGP</Mercato>
    <Ora>9</Ora>
    <PUN>122,060200</PUN>
    <NAT>120,090000</NAT>
    <CALA>117,000000</CALA>
    <CNOR>122,500000</CNOR>
    <CSUD>122,500000</CSUD>
    <NORD>122,500000</NORD>
    <SARD>122,500000</SARD>
    <SICI>117,000000</SICI>
    <SUD>122,500000</SUD>
    <AUST>122,500000</AUST>
    <COAC>122,500000</COAC>
    <COUP>122,500000</COUP>
    <CORS>122,500000</CORS>
    <FRAN>122,500000</FRAN>
    <GREC>122,500000</GREC>
    <SLOV>122,500000</SLOV>
    <SVIZ>122,500000</SVIZ>
    <BSP>122,500000</BSP>
    <MALT>117,000000</MALT>
    <XAUS>122,500000</XAUS>
    <XFRA>122,500000</XFRA>
    <MONT>122,500000</MONT>
    <XGRE>122,500000</XGRE>
  </Prezzi>
  <Prezzi>
    <Data>20240723</Data>
    <Mercato>MGP</Mercato>
    <Ora>10</Ora>
    <PUN>106,770000</PUN>
    <NAT>106,770000</NAT>
    <CALA>106,770000</CALA>
    <CNOR>106,770000</CNOR>
    <CSUD>106,770000</CSUD>
    <NORD>106,770000</NORD>
    <SARD>106,770000</SARD>
    <SICI>106,770000</SICI>
    <SUD>106,770000</SUD>
    <AUST>106,770000</AUST>
    <COAC>106,770000</COAC>
    <COUP>106,770000</COUP>
    <CORS>106,770000</CORS>
    <FRAN>106,770000</FRAN>
    <GREC>106,770000</GREC>
    <SLOV>106,770000</SLOV>
    <SVIZ>106,770000</SVIZ>
    <BSP>106,770000</BSP>
    <MALT>106,770000</MALT>
    <XAUS>106,770000</XAUS>
    <XFRA>106,770000</XFRA>
    <MONT>106,770000</MONT>
    <XGRE>106,770000</XGRE>
  </Prezzi>
  <Prezzi>
    <Data>20240723</Data>
    <Mercato>MGP</Mercato>
    <Ora>11</Ora>
    <PUN>100,800000</PUN>
    <NAT>100,800000</NAT>
    <CALA>100,800000</CALA>
    <CNOR>100,800000</CNOR>
    <CSUD>100,800000</CSUD>
    <NORD>100,800000</NORD>
    <SARD>100,800000</SARD>
    <SICI>100,800000</SICI>
    <SUD>100,800000</SUD>
    <AUST>100,800000</AUST>
    <COAC>100,800000</COAC>
    <COUP>100,800000</COUP>
    <CORS>100,800000</CORS>
    <FRAN>100,800000</FRAN>
    <GREC>100,800000</GREC>
    <SLOV>100,800000</SLOV>
    <SVIZ>100,800000</SVIZ>
    <BSP>100,800000</BSP>
    <MALT>100,800000</MALT>
    <XAUS>100,800000</XAUS>
    <XFRA>100,800000</XFRA>
    <MONT>100,800000</MONT>
    <XGRE>100,800000</XGRE>
  </Prezzi>
  <Prezzi>
    <Data>20240723</Data>
    <Mercato>MGP</Mercato>
    <Ora>12</Ora>
    <PUN>99,000000</PUN>
    <NAT>99,000000</NAT>
    <CALA>99,000000</CALA>
    <CNOR>99,000000</CNOR>
    <CSUD>99,000000</CSUD>
    <NORD>99,000000</NORD>
    <SARD>99,000000</SARD>
    <SICI>99,000000</SICI>
    <SUD>99,000000</SUD>
    <AUST>99,000000</AUST>
    <COAC>99,000000</COAC>
    <COUP>99,000000</COUP>
    <CORS>99,000000</CORS>
    <FRAN>99,000000</FRAN>
    <GREC>99,000000</GREC>
    <SLOV>99,000000</SLOV>
    <SVIZ>99,000000</SVIZ>
    <BSP>99,000000</BSP>
    <MALT>99,000000</MALT>
    <XAUS>99,000000</XAUS>
    <XFRA>99,000000</XFRA>
    <MONT>99,000000</MONT>
    <XGRE>99,000000</XGRE>
  </Prezzi>
  <Prezzi>
    <Data>20240723</Data>
    <Mercato>MGP</Mercato>
    <Ora>13</Ora>
    <PUN>97,790000</PUN>
    <NAT>97,790000</NAT>
    <CALA>97,790000</CALA>
    <CNOR>97,790000</CNOR>
    <CSUD>97,790000</CSUD>
    <NORD>97,790000</NORD>
    <SARD>97,790000</SARD>
    <SICI>97,790000</SICI>
    <SUD>97,790000</SUD>
    <AUST>97,790000</AUST>
    <COAC>97,790000</COAC>
    <COUP>97,790000</COUP>
    <CORS>97,790000</CORS>
    <FRAN>97,790000</FRAN>
    <GREC>97,790000</GREC>
    <SLOV>97,790000</SLOV>
    <SVIZ>97,790000</SVIZ>
    <BSP>97,790000</BSP>
    <MALT>97,790000</MALT>
    <XAUS>97,790000</XAUS>
    <XFRA>97,790000</XFRA>
    <MONT>97,790000</MONT>
    <XGRE>97,790000</XGRE>
  </Prezzi>
  <Prezzi>
    <Data>20240723</Data>
    <Mercato>MGP</Mercato>
    <Ora>14</Ora>
    <PUN>99,990000</PUN>
    <NAT>99,990000</NAT>
    <CALA>99,990000</CALA>
    <CNOR>99,990000</CNOR>
    <CSUD>99,990000</CSUD>
    <NORD>99,990000</NORD>
    <SARD>99,990000</SARD>
    <SICI>99,990000</SICI>
    <SUD>99,990000</SUD>
    <AUST>99,990000</AUST>
    <COAC>99,990000</COAC>
    <COUP>99,990000</COUP>
    <CORS>99,990000</CORS>
    <FRAN>99,990000</FRAN>
    <GREC>99,990000</GREC>
    <SLOV>99,990000</SLOV>
    <SVIZ>99,990000</SVIZ>
    <BSP>99,990000</BSP>
    <MALT>99,990000</MALT>
    <XAUS>99,990000</XAUS>
    <XFRA>99,990000</XFRA>
    <MONT>99,990000</MONT>
    <XGRE>99,990000</XGRE>
  </Prezzi>
  <Prezzi>
    <Data>20240723</Data>
    <Mercato>MGP</Mercato>
    <Ora>15</Ora>
    <PUN>103,080000</PUN>
    <NAT>103,080000</NAT>
    <CALA>103,080000</CALA>
    <CNOR>103,080000</CNOR>
    <CSUD>103,080000</CSUD>
    <NORD>103,080000</NORD>
    <SARD>103,080000</SARD>
    <SICI>103,080000</SICI>
    <SUD>103,080000</SUD>
    <AUST>103,080000</AUST>
    <COAC>103,080000</COAC>
    <COUP>103,080000</COUP>
    <CORS>103,080000</CORS>
    <FRAN>103,080000</FRAN>
    <GREC>103,080000</GREC>
    <SLOV>103,080000</SLOV>
    <SVIZ>103,080000</SVIZ>
    <BSP>103,080000</BSP>
    <MALT>103,080000</MALT>
    <XAUS>103,080000</XAUS>
    <XFRA>103,080000</XFRA>
    <MONT>103,080000</MONT>
    <XGRE>103,080000</XGRE>
  </Prezzi>
  <Prezzi>
    <Data>20240723</Data>
    <Mercato>MGP</Mercato>
    <Ora>16</Ora>
    <PUN>108,040000</PUN>
    <NAT>108,040000</NAT>
    <CALA>108,040000</CALA>
    <CNOR>108,040000</CNOR>
    <CSUD>108,040000</CSUD>
    <NORD>108,040000</NORD>
    <SARD>108,040000</SARD>
    <SICI>108,040000</SICI>
    <SUD>108,040000</SUD>
    <AUST>108,040000</AUST>
    <COAC>108,040000</COAC>
    <COUP>108,040000</COUP>
    <CORS>108,040000</CORS>
    <FRAN>108,040000</FRAN>
    <GREC>108,040000</GREC>
    <SLOV>108,040000</SLOV>
    <SVIZ>108,040000</SVIZ>
    <BSP>108,040000</BSP>
    <MALT>108,040000</MALT>
    <XAUS>108,040000</XAUS>
    <XFRA>108,040000</XFRA>
    <MONT>108,040000</MONT>
    <XGRE>108,040000</XGRE>
  </Prezzi>
  <Prezzi>
    <Data>20240723</Data>
    <Mercato>MGP</Mercato>
    <Ora>17</Ora>
    <PUN>108,040000</PUN>
    <NAT>108,040000</NAT>
    <CALA>108,040000</CALA>
    <CNOR>108,040000</CNOR>
    <CSUD>108,040000</CSUD>
    <NORD>108,040000</NORD>
    <SARD>108,040000</SARD>
    <SICI>108,040000</SICI>
    <SUD>108,040000</SUD>
    <AUST>108,040000</AUST>
    <COAC>108,040000</COAC>
    <COUP>108,040000</COUP>
    <CORS>108,040000</CORS>
    <FRAN>108,040000</FRAN>
    <GREC>108,040000</GREC>
    <SLOV>108,040000</SLOV>
    <SVIZ>108,040000</SVIZ>
    <BSP>108,040000</BSP>
    <MALT>108,040000</MALT>
    <XAUS>108,040000</XAUS>
    <XFRA>108,040000</XFRA>
    <MONT>108,040000</MONT>
    <XGRE>108,040000</XGRE>
  </Prezzi>
  <Prezzi>
    <Data>20240723</Data>
    <Mercato>MGP</Mercato>
    <Ora>18</Ora>
    <PUN>108,040000</PUN>
    <NAT>108,040000</NAT>
    <CALA>108,040000</CALA>
    <CNOR>108,040000</CNOR>
    <CSUD>108,040000</CSUD>
    <NORD>108,040000</NORD>
    <SARD>108,040000</SARD>
    <SICI>108,040000</SICI>
    <SUD>108,040000</SUD>
    <AUST>108,040000</AUST>
    <COAC>108,040000</COAC>
    <COUP>108,040000</COUP>
    <CORS>108,040000</CORS>
    <FRAN>108,040000</FRAN>
    <GREC>108,040000</GREC>
    <SLOV>108,040000</SLOV>
    <SVIZ>108,040000</SVIZ>
    <BSP>108,040000</BSP>
    <MALT>108,040000</MALT>
    <XAUS>108,040000</XAUS>
    <XFRA>108,040000</XFRA>
    <MONT>108,040000</MONT>
    <XGRE>108,040000</XGRE>
  </Prezzi>
  <Prezzi>
    <Data>20240723</Data>
    <Mercato>MGP</Mercato>
    <Ora>19</Ora>
    <PUN>131,438060</PUN>
    <NAT>130,730000</NAT>
    <CALA>124,110000</CALA>
    <CNOR>132,120000</CNOR>
    <CSUD>132,120000</CSUD>
    <NORD>132,120000</NORD>
    <SARD>132,120000</SARD>
    <SICI>124,110000</SICI>
    <SUD>132,120000</SUD>
    <AUST>132,120000</AUST>
    <COAC>132,120000</COAC>
    <COUP>132,120000</COUP>
    <CORS>132,120000</CORS>
    <FRAN>132,120000</FRAN>
    <GREC>132,120000</GREC>
    <SLOV>132,120000</SLOV>
    <SVIZ>132,120000</SVIZ>
    <BSP>132,120000</BSP>
    <MALT>124,110000</MALT>
    <XAUS>132,120000</XAUS>
    <XFRA>132,120000</XFRA>
    <MONT>132,120000</MONT>
    <XGRE>132,120000</XGRE>
  </Prezzi>
  <Prezzi>
    <Data>20240723</Data>
    <Mercato>MGP</Mercato>
    <Ora>20</Ora>
    <PUN>158,912680</PUN>
    <NAT>158,000000</NAT>
    <CALA>160,000000</CALA>
    <CNOR>160,000000</CNOR>
    <CSUD>160,000000</CSUD>
    <NORD>158,000000</NORD>
    <SARD>160,000000</SARD>
    <SICI>160,000000</SICI>
    <SUD>160,000000</SUD>
    <AUST>158,000000</AUST>
    <COAC>160,000000</COAC>
    <COUP>158,000000</COUP>
    <CORS>160,000000</CORS>
    <FRAN>158,000000</FRAN>
    <GREC>160,000000</GREC>
    <SLOV>158,000000</SLOV>
    <SVIZ>158,000000</SVIZ>
    <BSP>158,000000</BSP>
    <MALT>160,000000</MALT>
    <XAUS>158,000000</XAUS>
    <XFRA>158,000000</XFRA>
    <MONT>160,000000</MONT>
    <XGRE>160,000000</XGRE>
  </Prezzi>
  <Prezzi>
    <Data>20240723</Data>
    <Mercato>MGP</Mercato>
    <Ora>21</Ora>
    <PUN>178,856040</PUN>
    <NAT>167,900000</NAT>
    <CALA>199,670000</CALA>
    <CNOR>199,670000</CNOR>
    <CSUD>199,670000</CSUD>
    <NORD>161,050000</NORD>
    <SARD>199,670000</SARD>
    <SICI>199,670000</SICI>
    <SUD>199,670000</SUD>
    <AUST>161,050000</AUST>
    <COAC>199,670000</COAC>
    <COUP>161,050000</COUP>
    <CORS>199,670000</CORS>
    <FRAN>161,050000</FRAN>
    <GREC>199,670000</GREC>
    <SLOV>161,050000</SLOV>
    <SVIZ>161,050000</SVIZ>
    <BSP>161,050000</BSP>
    <MALT>199,670000</MALT>
    <XAUS>161,050000</XAUS>
    <XFRA>161,050000</XFRA>
    <MONT>199,670000</MONT>
    <XGRE>199,670000</XGRE>
  </Prezzi>
  <Prezzi>
    <Data>20240723</Data>
    <Mercato>MGP</Mercato>
    <Ora>22</Ora>
    <PUN>160,000000</PUN>
    <NAT>156,860000</NAT>
    <CALA>169,867540</CALA>
    <CNOR>169,867540</CNOR>
    <CSUD>169,867540</CSUD>
    <NORD>151,580000</NORD>
    <SARD>169,867540</SARD>
    <SICI>169,867540</SICI>
    <SUD>169,867540</SUD>
    <AUST>151,580000</AUST>
    <COAC>169,867540</COAC>
    <COUP>151,580000</COUP>
    <CORS>169,867540</CORS>
    <FRAN>151,580000</FRAN>
    <GREC>169,867540</GREC>
    <SLOV>151,580000</SLOV>
    <SVIZ>151,580000</SVIZ>
    <BSP>151,580000</BSP>
    <MALT>169,867540</MALT>
    <XAUS>151,580000</XAUS>
    <XFRA>151,580000</XFRA>
    <MONT>169,867540</MONT>
    <XGRE>169,867540</XGRE>
  </Prezzi>
  <Prezzi>
    <Data>20240723</Data>
    <Mercato>MGP</Mercato>
    <Ora>23</Ora>
    <PUN>119,921130</PUN>
    <NAT>120,000000</NAT>
    <CALA>121,000000</CALA>
    <CNOR>121,000000</CNOR>
    <CSUD>121,000000</CSUD>
    <NORD>119,000000</NORD>
    <SARD>121,000000</SARD>
    <SICI>121,000000</SICI>
    <SUD>121,000000</SUD>
    <AUST>119,000000</AUST>
    <COAC>121,000000</COAC>
    <COUP>119,000000</COUP>
    <CORS>121,000000</CORS>
    <FRAN>119,000000</FRAN>
    <GREC>121,000000</GREC>
    <SLOV>119,000000</SLOV>
    <SVIZ>119,000000</SVIZ>
    <BSP>119,000000</BSP>
    <MALT>121,000000</MALT>
    <XAUS>119,000000</XAUS>
    <XFRA>119,000000</XFRA>
    <MONT>121,000000</MONT>
    <XGRE>121,000000</XGRE>
  </Prezzi>
  <Prezzi>
    <Data>20240723</Data>
    <Mercato>MGP</Mercato>
    <Ora>24</Ora>
    <PUN>108,080000</PUN>
    <NAT>108,080000</NAT>
    <CALA>108,080000</CALA>
    <CNOR>108,080000</CNOR>
    <CSUD>108,080000</CSUD>
    <NORD>108,080000</NORD>
    <SARD>108,080000</SARD>
    <SICI>108,080000</SICI>
    <SUD>108,080000</SUD>
    <AUST>108,080000</AUST>
    <COAC>108,080000</COAC>
    <COUP>108,080000</COUP>
    <CORS>108,080000</CORS>
    <FRAN>108,080000</FRAN>
    <GREC>108,080000</GREC>
    <SLOV>108,080000</SLOV>
    <SVIZ>108,080000</SVIZ>
    <BSP>108,080000</BSP>
    <MALT>108,080000</MALT>
    <XAUS>108,080000</XAUS>
    <XFRA>108,080000</XFRA>
    <MONT>108,080000</MONT>
    <XGRE>108,080000</XGRE>
  </Prezzi>
</NewDataSet>