<?xml version="1.0" standalone="yes"?>
<NewDataSet>
  <xs:schema id="NewDataSet" xmlns="" xmlns:xs="http://www.w3.org/2001/XMLSchema" xmlns:msdata="urn:schemas-microsoft-com:xml-msdata">
    <xs:element name="NewDataSet" msdata:IsDataSet="true" msdata:UseCurrentLocale="true">
      <xs:complexType>
        <xs:choice minOccurs="0" maxOccurs="unbounded">
          <xs:element name="Prezzi">
            <xs:complexType>
              <xs:sequence>
                <xs:element name="Data" type="xs:string" minOccurs="0" />
                <xs:element name="Mercato" type="xs:string" minOccurs="0" />
                <xs:element name="Ora" type="xs:string" minOccurs="0" />
                <xs:element name="PUN" type="xs:string" minOccurs="0" />
                <xs:element name="NAT" type="xs:string" minOccurs="0" />
                <xs:element name="CALA" type="xs:string" minOccurs="0" />
                <xs:element name="CNOR" type="xs:string" minOccurs="0" />
                <xs:element name="CSUD" type="xs:string" minOccurs="0" />
                <xs:element name="NORD" type="xs:string" minOccurs="0" />
                <xs:element name="SARD" type="xs:string" minOccurs="0" />
                <xs:element name="SICI" type="xs:string" minOccurs="0" />
                <xs:element name="SUD" type="xs:string" minOccurs="0" />
                <xs:element name="AUST" type="xs:string" minOccurs="0" />
                <xs:element name="COAC" type="xs:string" minOccurs="0" />
                <xs:element name="COUP" type="xs:string" minOccurs="0" />
                <xs:element name="CORS" type="xs:string" minOccurs="0" />
                <xs:element name="FRAN" type="xs:string" minOccurs="0" />
                <xs:element name="GREC" type="xs:string" minOccurs="0" />
                <xs:element name="SLOV" type="xs:string" minOccurs="0" />
                <xs:element name="SVIZ" type="xs:string" minOccurs="0" />
                <xs:element name="BSP" type="xs:string" minOccurs="0" />
                <xs:element name="MALT" type="xs:string" minOccurs="0" />
                <xs:element name="XAUS" type="xs:string" minOccurs="0" />
                <xs:element name="XFRA" type="xs:string" minOccurs="0" />
                <xs:element name="MONT" type="xs:string" minOccurs="0" />
                <xs:element name="XGRE" type="xs:string" minOccurs="0" />
              </xs:sequence>
            </xs:complexType>
          </xs:element>
        </xs:choice>
      </xs:complexType>
    </xs:element>
  </xs:schema>
  <Prezzi>
    <Data>20250827</Data>
    <Mercato>MGP</Mercato>
    <Ora>1</Ora>
    <PUN>110,920690</PUN>
    <NAT>125,180000</NAT>
    <CALA>112,000000</CALA>
    <CNOR>112,000000</CNOR>
    <CSUD>112,000000</CSUD>
    <NORD>110,000000</NORD>
    <SARD>112,000000</SARD>
    <SICI>112,000000</SICI>
    <SUD>112,000000</SUD>
    <AUST>110,000000</AUST>
    <COAC>112,000000</COAC>
    <COUP>110,000000</COUP>
    <CORS>112,000000</CORS>
    <FRAN>110,000000</FRAN>
    <GREC>112,000000</GREC>
    <SLOV>110,000000</SLOV>
    <SVIZ>110,000000</SVIZ>
    <BSP>110,000000</BSP>
    <MALT>112,000000</MALT>
    <XAUS>110,000000</XAUS>
    <XFRA>110,000000</XFRA>
    <MONT>112,000000</MONT>
    <XGRE>112,000000</XGRE>
  </Prezzi>
  <Prezzi>
    <Data>20250827</Data>
    <Mercato>MGP</Mercato>
    <Ora>2</Ora>
    <PUN>105,571030</PUN>
    <NAT>120,000000</NAT>
    <CALA>106,230000</CALA>
    <CNOR>106,230000</CNOR>
    <CSUD>106,230000</CSUD>
    <NORD>105,030000</NORD>
    <SARD>106,230000</SARD>
    <SICI>106,230000</SICI>
    <SUD>106,230000</SUD>
    <AUST>105,030000</AUST>
    <COAC>106,230000</COAC>
    <COUP>105,030000</COUP>
    <CORS>106,230000</CORS>
    <FRAN>105,030000</FRAN>
    <GREC>106,230000</GREC>
    <SLOV>105,030000</SLOV>
    <SVIZ>105,030000</SVIZ>
    <BSP>105,030000</BSP>
    <MALT>106,230000</MALT>
    <XAUS>105,030000</XAUS>
    <XFRA>105,030000</XFRA>
    <MONT>106,230000</MONT>
    <XGRE>106,230000</XGRE>
  </Prezzi>
  <Prezzi>
    <Data>20250827</Data>
    <Mercato>MGP</Mercato>
    <Ora>3</Ora>
    <PUN>102,973020</PUN>
    <NAT>119,990000</NAT>
    <CALA>108,560000</CALA>
    <CNOR>108,560000</CNOR>
    <CSUD>108,560000</CSUD>
    <NORD>98,370000</NORD>
    <SARD>108,560000</SARD>
    <SICI>108,560000</SICI>
    <SUD>108,560000</SUD>
    <AUST>98,370000</AUST>
    <COAC>108,560000</COAC>
    <COUP>98,370000</COUP>
    <CORS>108,560000</CORS>
    <FRAN>98,370000</FRAN>
    <GREC>108,560000</GREC>
    <SLOV>98,370000</SLOV>
    <SVIZ>98,370000</SVIZ>
    <BSP>98,370000</BSP>
    <MALT>108,560000</MALT>
    <XAUS>98,370000</XAUS>
    <XFRA>98,370000</XFRA>
    <MONT>108,560000</MONT>
    <XGRE>108,560000</XGRE>
  </Prezzi>
  <Prezzi>
    <Data>20250827</Data>
    <Mercato>MGP</Mercato>
    <Ora>4</Ora>
    <PUN>102,016770</PUN>
    <NAT>115,000000</NAT>
    <CALA>105,100000</CALA>
    <CNOR>105,100000</CNOR>
    <CSUD>105,100000</CSUD>
    <NORD>99,500000</NORD>
    <SARD>105,100000</SARD>
    <SICI>105,100000</SICI>
    <SUD>105,100000</SUD>
    <AUST>99,500000</AUST>
    <COAC>105,100000</COAC>
    <COUP>99,500000</COUP>
    <CORS>105,100000</CORS>
    <FRAN>99,500000</FRAN>
    <GREC>105,100000</GREC>
    <SLOV>99,500000</SLOV>
    <SVIZ>99,500000</SVIZ>
    <BSP>99,500000</BSP>
    <MALT>105,100000</MALT>
    <XAUS>99,500000</XAUS>
    <XFRA>99,500000</XFRA>
    <MONT>105,100000</MONT>
    <XGRE>105,100000</XGRE>
  </Prezzi>
  <Prezzi>
    <Data>20250827</Data>
    <Mercato>MGP</Mercato>
    <Ora>5</Ora>
    <PUN>105,020000</PUN>
    <NAT>115,200000</NAT>
    <CALA>105,020000</CALA>
    <CNOR>105,020000</CNOR>
    <CSUD>105,020000</CSUD>
    <NORD>105,020000</NORD>
    <SARD>105,020000</SARD>
    <SICI>105,020000</SICI>
    <SUD>105,020000</SUD>
    <AUST>105,020000</AUST>
    <COAC>105,020000</COAC>
    <COUP>105,020000</COUP>
    <CORS>105,020000</CORS>
    <FRAN>105,020000</FRAN>
    <GREC>105,020000</GREC>
    <SLOV>105,020000</SLOV>
    <SVIZ>105,020000</SVIZ>
    <BSP>105,020000</BSP>
    <MALT>105,020000</MALT>
    <XAUS>105,020000</XAUS>
    <XFRA>105,020000</XFRA>
    <MONT>105,020000</MONT>
    <XGRE>105,020000</XGRE>
  </Prezzi>
  <Prezzi>
    <Data>20250827</Data>
    <Mercato>MGP</Mercato>
    <Ora>6</Ora>
    <PUN>105,603130</PUN>
    <NAT>119,990000</NAT>
    <CALA>106,230000</CALA>
    <CNOR>106,230000</CNOR>
    <CSUD>106,230000</CSUD>
    <NORD>105,100000</NORD>
    <SARD>106,230000</SARD>
    <SICI>106,230000</SICI>
    <SUD>106,230000</SUD>
    <AUST>105,100000</AUST>
    <COAC>106,230000</COAC>
    <COUP>105,100000</COUP>
    <CORS>106,230000</CORS>
    <FRAN>105,100000</FRAN>
    <GREC>106,230000</GREC>
    <SLOV>105,100000</SLOV>
    <SVIZ>105,100000</SVIZ>
    <BSP>105,100000</BSP>
    <MALT>106,230000</MALT>
    <XAUS>105,100000</XAUS>
    <XFRA>105,100000</XFRA>
    <MONT>106,230000</MONT>
    <XGRE>106,230000</XGRE>
  </Prezzi>
  <Prezzi>
    <Data>20250827</Data>
    <Mercato>MGP</Mercato>
    <Ora>7</Ora>
    <PUN>114,320000</PUN>
    <NAT>125,180000</NAT>
    <CALA>114,320000</CALA>
    <CNOR>114,320000</CNOR>
    <CSUD>114,320000</CSUD>
    <NORD>114,320000</NORD>
    <SARD>114,320000</SARD>
    <SICI>114,320000</SICI>
    <SUD>114,320000</SUD>
    <AUST>114,320000</AUST>
    <COAC>114,320000</COAC>
    <COUP>114,320000</COUP>
    <CORS>114,320000</CORS>
    <FRAN>114,320000</FRAN>
    <GREC>114,320000</GREC>
    <SLOV>114,320000</SLOV>
    <SVIZ>114,320000</SVIZ>
    <BSP>114,320000</BSP>
    <MALT>114,320000</MALT>
    <XAUS>114,320000</XAUS>
    <XFRA>114,320000</XFRA>
    <MONT>114,320000</MONT>
    <XGRE>114,320000</XGRE>
  </Prezzi>
  <Prezzi>
    <Data>20250827</Data>
    <Mercato>MGP</Mercato>
    <Ora>8</Ora>
    <PUN>124,952420</PUN>
    <NAT>132,350000</NAT>
    <CALA>129,000000</CALA>
    <CNOR>129,000000</CNOR>
    <CSUD>129,000000</CSUD>
    <NORD>129,000000</NORD>
    <SARD>0,000000</SARD>
    <SICI>129,000000</SICI>
    <SUD>129,000000</SUD>
    <AUST>129,000000</AUST>
    <COAC>0,000000</COAC>
    <COUP>129,000000</COUP>
    <CORS>129,000000</CORS>
    <FRAN>129,000000</FRAN>
    <GREC>129,000000</GREC>
    <SLOV>129,000000</SLOV>
    <SVIZ>129,000000</SVIZ>
    <BSP>129,000000</BSP>
    <MALT>129,000000</MALT>
    <XAUS>129,000000</XAUS>
    <XFRA>129,000000</XFRA>
    <MONT>129,000000</MONT>
    <XGRE>129,000000</XGRE>
  </Prezzi>
  <Prezzi>
    <Data>20250827</Data>
    <Mercato>MGP</Mercato>
    <Ora>9</Ora>
    <PUN>126,562090</PUN>
    <NAT>132,350000</NAT>
    <CALA>130,000000</CALA>
    <CNOR>130,000000</CNOR>
    <CSUD>130,000000</CSUD>
    <NORD>130,000000</NORD>
    <SARD>17,000000</SARD>
    <SICI>130,000000</SICI>
    <SUD>130,000000</SUD>
    <AUST>130,000000</AUST>
    <COAC>17,000000</COAC>
    <COUP>130,000000</COUP>
    <CORS>130,000000</CORS>
    <FRAN>130,000000</FRAN>
    <GREC>130,000000</GREC>
    <SLOV>130,000000</SLOV>
    <SVIZ>130,000000</SVIZ>
    <BSP>130,000000</BSP>
    <MALT>130,000000</MALT>
    <XAUS>130,000000</XAUS>
    <XFRA>130,000000</XFRA>
    <MONT>130,000000</MONT>
    <XGRE>130,000000</XGRE>
  </Prezzi>
  <Prezzi>
    <Data>20250827</Data>
    <Mercato>MGP</Mercato>
    <Ora>10</Ora>
    <PUN>128,302270</PUN>
    <NAT>128,180000</NAT>
    <CALA>132,350000</CALA>
    <CNOR>132,350000</CNOR>
    <CSUD>132,350000</CSUD>
    <NORD>132,350000</NORD>
    <SARD>0,000000</SARD>
    <SICI>132,350000</SICI>
    <SUD>132,350000</SUD>
    <AUST>132,350000</AUST>
    <COAC>0,000000</COAC>
    <COUP>132,350000</COUP>
    <CORS>132,350000</CORS>
    <FRAN>132,350000</FRAN>
    <GREC>132,350000</GREC>
    <SLOV>132,350000</SLOV>
    <SVIZ>132,350000</SVIZ>
    <BSP>132,350000</BSP>
    <MALT>132,350000</MALT>
    <XAUS>132,350000</XAUS>
    <XFRA>132,350000</XFRA>
    <MONT>132,350000</MONT>
    <XGRE>132,350000</XGRE>
  </Prezzi>
  <Prezzi>
    <Data>20250827</Data>
    <Mercato>MGP</Mercato>
    <Ora>11</Ora>
    <PUN>117,251570</PUN>
    <NAT>125,180000</NAT>
    <CALA>121,000000</CALA>
    <CNOR>121,000000</CNOR>
    <CSUD>121,000000</CSUD>
    <NORD>121,000000</NORD>
    <SARD>0,000000</SARD>
    <SICI>121,000000</SICI>
    <SUD>121,000000</SUD>
    <AUST>121,000000</AUST>
    <COAC>0,000000</COAC>
    <COUP>121,000000</COUP>
    <CORS>121,000000</CORS>
    <FRAN>121,000000</FRAN>
    <GREC>121,000000</GREC>
    <SLOV>121,000000</SLOV>
    <SVIZ>121,000000</SVIZ>
    <BSP>121,000000</BSP>
    <MALT>121,000000</MALT>
    <XAUS>121,000000</XAUS>
    <XFRA>121,000000</XFRA>
    <MONT>121,000000</MONT>
    <XGRE>121,000000</XGRE>
  </Prezzi>
  <Prezzi>
    <Data>20250827</Data>
    <Mercato>MGP</Mercato>
    <Ora>12</Ora>
    <PUN>116,318910</PUN>
    <NAT>120,880000</NAT>
    <CALA>120,000000</CALA>
    <CNOR>120,000000</CNOR>
    <CSUD>120,000000</CSUD>
    <NORD>120,000000</NORD>
    <SARD>0,000000</SARD>
    <SICI>120,000000</SICI>
    <SUD>120,000000</SUD>
    <AUST>120,000000</AUST>
    <COAC>0,000000</COAC>
    <COUP>120,000000</COUP>
    <CORS>120,000000</CORS>
    <FRAN>120,000000</FRAN>
    <GREC>120,000000</GREC>
    <SLOV>120,000000</SLOV>
    <SVIZ>120,000000</SVIZ>
    <BSP>120,000000</BSP>
    <MALT>120,000000</MALT>
    <XAUS>120,000000</XAUS>
    <XFRA>120,000000</XFRA>
    <MONT>120,000000</MONT>
    <XGRE>120,000000</XGRE>
  </Prezzi>
  <Prezzi>
    <Data>20250827</Data>
    <Mercato>MGP</Mercato>
    <Ora>13</Ora>
    <PUN>107,418630</PUN>
    <NAT>115,000000</NAT>
    <CALA>111,000000</CALA>
    <CNOR>111,000000</CNOR>
    <CSUD>111,000000</CSUD>
    <NORD>111,000000</NORD>
    <SARD>0,000000</SARD>
    <SICI>111,000000</SICI>
    <SUD>111,000000</SUD>
    <AUST>111,000000</AUST>
    <COAC>0,000000</COAC>
    <COUP>111,000000</COUP>
    <CORS>111,000000</CORS>
    <FRAN>111,000000</FRAN>
    <GREC>111,000000</GREC>
    <SLOV>111,000000</SLOV>
    <SVIZ>111,000000</SVIZ>
    <BSP>111,000000</BSP>
    <MALT>111,000000</MALT>
    <XAUS>111,000000</XAUS>
    <XFRA>111,000000</XFRA>
    <MONT>111,000000</MONT>
    <XGRE>111,000000</XGRE>
  </Prezzi>
  <Prezzi>
    <Data>20250827</Data>
    <Mercato>MGP</Mercato>
    <Ora>14</Ora>
    <PUN>109,169170</PUN>
    <NAT>117,000000</NAT>
    <CALA>112,810000</CALA>
    <CNOR>112,810000</CNOR>
    <CSUD>112,810000</CSUD>
    <NORD>112,810000</NORD>
    <SARD>0,000000</SARD>
    <SICI>112,810000</SICI>
    <SUD>112,810000</SUD>
    <AUST>112,810000</AUST>
    <COAC>0,000000</COAC>
    <COUP>112,810000</COUP>
    <CORS>112,810000</CORS>
    <FRAN>112,810000</FRAN>
    <GREC>112,810000</GREC>
    <SLOV>112,810000</SLOV>
    <SVIZ>112,810000</SVIZ>
    <BSP>112,810000</BSP>
    <MALT>112,810000</MALT>
    <XAUS>112,810000</XAUS>
    <XFRA>112,810000</XFRA>
    <MONT>112,810000</MONT>
    <XGRE>112,810000</XGRE>
  </Prezzi>
  <Prezzi>
    <Data>20250827</Data>
    <Mercato>MGP</Mercato>
    <Ora>15</Ora>
    <PUN>111,337190</PUN>
    <NAT>120,880000</NAT>
    <CALA>115,000000</CALA>
    <CNOR>115,000000</CNOR>
    <CSUD>115,000000</CSUD>
    <NORD>115,000000</NORD>
    <SARD>0,000000</SARD>
    <SICI>115,000000</SICI>
    <SUD>115,000000</SUD>
    <AUST>115,000000</AUST>
    <COAC>0,000000</COAC>
    <COUP>115,000000</COUP>
    <CORS>115,000000</CORS>
    <FRAN>115,000000</FRAN>
    <GREC>115,000000</GREC>
    <SLOV>115,000000</SLOV>
    <SVIZ>115,000000</SVIZ>
    <BSP>115,000000</BSP>
    <MALT>115,000000</MALT>
    <XAUS>115,000000</XAUS>
    <XFRA>115,000000</XFRA>
    <MONT>115,000000</MONT>
    <XGRE>115,000000</XGRE>
  </Prezzi>
  <Prezzi>
    <Data>20250827</Data>
    <Mercato>MGP</Mercato>
    <Ora>16</Ora>
    <PUN>118,356060</PUN>
    <NAT>125,180000</NAT>
    <CALA>122,140000</CALA>
    <CNOR>122,140000</CNOR>
    <CSUD>122,140000</CSUD>
    <NORD>122,140000</NORD>
    <SARD>0,000000</SARD>
    <SICI>122,140000</SICI>
    <SUD>122,140000</SUD>
    <AUST>122,140000</AUST>
    <COAC>0,000000</COAC>
    <COUP>122,140000</COUP>
    <CORS>122,140000</CORS>
    <FRAN>122,140000</FRAN>
    <GREC>122,140000</GREC>
    <SLOV>122,140000</SLOV>
    <SVIZ>122,140000</SVIZ>
    <BSP>122,140000</BSP>
    <MALT>122,140000</MALT>
    <XAUS>122,140000</XAUS>
    <XFRA>122,140000</XFRA>
    <MONT>122,140000</MONT>
    <XGRE>122,140000</XGRE>
  </Prezzi>
  <Prezzi>
    <Data>20250827</Data>
    <Mercato>MGP</Mercato>
    <Ora>17</Ora>
    <PUN>111,427140</PUN>
    <NAT>125,180000</NAT>
    <CALA>115,000000</CALA>
    <CNOR>115,000000</CNOR>
    <CSUD>115,000000</CSUD>
    <NORD>115,000000</NORD>
    <SARD>0,000000</SARD>
    <SICI>115,000000</SICI>
    <SUD>115,000000</SUD>
    <AUST>115,000000</AUST>
    <COAC>0,000000</COAC>
    <COUP>115,000000</COUP>
    <CORS>115,000000</CORS>
    <FRAN>115,000000</FRAN>
    <GREC>115,000000</GREC>
    <SLOV>115,000000</SLOV>
    <SVIZ>115,000000</SVIZ>
    <BSP>115,000000</BSP>
    <MALT>115,000000</MALT>
    <XAUS>115,000000</XAUS>
    <XFRA>115,000000</XFRA>
    <MONT>115,000000</MONT>
    <XGRE>115,000000</XGRE>
  </Prezzi>
  <Prezzi>
    <Data>20250827</Data>
    <Mercato>MGP</Mercato>
    <Ora>18</Ora>
    <PUN>110,137790</PUN>
    <NAT>130,000000</NAT>
    <CALA>113,840000</CALA>
    <CNOR>113,840000</CNOR>
    <CSUD>113,840000</CSUD>
    <NORD>113,840000</NORD>
    <SARD>0,000000</SARD>
    <SICI>113,840000</SICI>
    <SUD>113,840000</SUD>
    <AUST>113,840000</AUST>
    <COAC>0,000000</COAC>
    <COUP>113,840000</COUP>
    <CORS>113,840000</CORS>
    <FRAN>113,840000</FRAN>
    <GREC>113,840000</GREC>
    <SLOV>113,840000</SLOV>
    <SVIZ>113,840000</SVIZ>
    <BSP>113,840000</BSP>
    <MALT>113,840000</MALT>
    <XAUS>113,840000</XAUS>
    <XFRA>113,840000</XFRA>
    <MONT>113,840000</MONT>
    <XGRE>113,840000</XGRE>
  </Prezzi>
  <Prezzi>
    <Data>20250827</Data>
    <Mercato>MGP</Mercato>
    <Ora>19</Ora>
    <PUN>129,800000</PUN>
    <NAT>137,180000</NAT>
    <CALA>129,800000</CALA>
    <CNOR>129,800000</CNOR>
    <CSUD>129,800000</CSUD>
    <NORD>129,800000</NORD>
    <SARD>129,800000</SARD>
    <SICI>129,800000</SICI>
    <SUD>129,800000</SUD>
    <AUST>129,800000</AUST>
    <COAC>129,800000</COAC>
    <COUP>129,800000</COUP>
    <CORS>129,800000</CORS>
    <FRAN>129,800000</FRAN>
    <GREC>129,800000</GREC>
    <SLOV>129,800000</SLOV>
    <SVIZ>129,800000</SVIZ>
    <BSP>129,800000</BSP>
    <MALT>129,800000</MALT>
    <XAUS>129,800000</XAUS>
    <XFRA>129,800000</XFRA>
    <MONT>129,800000</MONT>
    <XGRE>129,800000</XGRE>
  </Prezzi>
  <Prezzi>
    <Data>20250827</Data>
    <Mercato>MGP</Mercato>
    <Ora>20</Ora>
    <PUN>145,789530</PUN>
    <NAT>145,510000</NAT>
    <CALA>158,210000</CALA>
    <CNOR>158,210000</CNOR>
    <CSUD>158,210000</CSUD>
    <NORD>134,790000</NORD>
    <SARD>158,210000</SARD>
    <SICI>158,210000</SICI>
    <SUD>158,210000</SUD>
    <AUST>134,790000</AUST>
    <COAC>158,210000</COAC>
    <COUP>134,790000</COUP>
    <CORS>158,210000</CORS>
    <FRAN>134,790000</FRAN>
    <GREC>158,210000</GREC>
    <SLOV>134,790000</SLOV>
    <SVIZ>134,790000</SVIZ>
    <BSP>134,790000</BSP>
    <MALT>158,210000</MALT>
    <XAUS>134,790000</XAUS>
    <XFRA>134,790000</XFRA>
    <MONT>158,210000</MONT>
    <XGRE>158,210000</XGRE>
  </Prezzi>
  <Prezzi>
    <Data>20250827</Data>
    <Mercato>MGP</Mercato>
    <Ora>21</Ora>
    <PUN>152,364640</PUN>
    <NAT>149,470000</NAT>
    <CALA>158,770000</CALA>
    <CNOR>158,770000</CNOR>
    <CSUD>158,770000</CSUD>
    <NORD>146,540000</NORD>
    <SARD>158,770000</SARD>
    <SICI>158,770000</SICI>
    <SUD>158,770000</SUD>
    <AUST>146,540000</AUST>
    <COAC>158,770000</COAC>
    <COUP>146,540000</COUP>
    <CORS>158,770000</CORS>
    <FRAN>146,540000</FRAN>
    <GREC>158,770000</GREC>
    <SLOV>146,540000</SLOV>
    <SVIZ>146,540000</SVIZ>
    <BSP>146,540000</BSP>
    <MALT>158,770000</MALT>
    <XAUS>146,540000</XAUS>
    <XFRA>146,540000</XFRA>
    <MONT>158,770000</MONT>
    <XGRE>158,770000</XGRE>
  </Prezzi>
  <Prezzi>
    <Data>20250827</Data>
    <Mercato>MGP</Mercato>
    <Ora>22</Ora>
    <PUN>129,038740</PUN>
    <NAT>137,180000</NAT>
    <CALA>132,350000</CALA>
    <CNOR>132,350000</CNOR>
    <CSUD>132,350000</CSUD>
    <NORD>126,119170</NORD>
    <SARD>132,350000</SARD>
    <SICI>132,350000</SICI>
    <SUD>132,350000</SUD>
    <AUST>126,119170</AUST>
    <COAC>132,350000</COAC>
    <COUP>126,119170</COUP>
    <CORS>132,350000</CORS>
    <FRAN>126,119170</FRAN>
    <GREC>132,350000</GREC>
    <SLOV>126,119170</SLOV>
    <SVIZ>126,119170</SVIZ>
    <BSP>126,119170</BSP>
    <MALT>132,350000</MALT>
    <XAUS>126,119170</XAUS>
    <XFRA>126,119170</XFRA>
    <MONT>132,350000</MONT>
    <XGRE>132,350000</XGRE>
  </Prezzi>
  <Prezzi>
    <Data>20250827</Data>
    <Mercato>MGP</Mercato>
    <Ora>23</Ora>
    <PUN>119,464020</PUN>
    <NAT>135,410000</NAT>
    <CALA>125,000000</CALA>
    <CNOR>125,000000</CNOR>
    <CSUD>125,000000</CSUD>
    <NORD>114,640000</NORD>
    <SARD>125,000000</SARD>
    <SICI>125,000000</SICI>
    <SUD>125,000000</SUD>
    <AUST>114,640000</AUST>
    <COAC>125,000000</COAC>
    <COUP>114,640000</COUP>
    <CORS>125,000000</CORS>
    <FRAN>114,640000</FRAN>
    <GREC>125,000000</GREC>
    <SLOV>114,640000</SLOV>
    <SVIZ>114,640000</SVIZ>
    <BSP>114,640000</BSP>
    <MALT>125,000000</MALT>
    <XAUS>114,640000</XAUS>
    <XFRA>114,640000</XFRA>
    <MONT>125,000000</MONT>
    <XGRE>125,000000</XGRE>
  </Prezzi>
  <Prezzi>
    <Data>20250827</Data>
    <Mercato>MGP</Mercato>
    <Ora>24</Ora>
    <PUN>112,410000</PUN>
    <NAT>129,060000</NAT>
    <CALA>112,410000</CALA>
    <CNOR>112,410000</CNOR>
    <CSUD>112,410000</CSUD>
    <NORD>112,410000</NORD>
    <SARD>112,410000</SARD>
    <SICI>112,410000</SICI>
    <SUD>112,410000</SUD>
    <AUST>112,410000</AUST>
    <COAC>112,410000</COAC>
    <COUP>112,410000</COUP>
    <CORS>112,410000</CORS>
    <FRAN>112,410000</FRAN>
    <GREC>112,410000</GREC>
    <SLOV>112,410000</SLOV>
    <SVIZ>112,410000</SVIZ>
    <BSP>112,410000</BSP>
    <MALT>112,410000</MALT>
    <XAUS>112,410000</XAUS>
    <XFRA>112,410000</XFRA>
    <MONT>112,410000</MONT>
    <XGRE>112,410000</XGRE>
  </Prezzi>
</NewDataSet>